MANIFEST.in
setup.py
dnsmon/__init__.py
dnsmon/dnsmon.py
dnsmon/mailer.py
dnsmon/resolver.py
dnsmon/settings.py
dnsmon/settings_local.py.example
dnsmon.egg-info/PKG-INFO
dnsmon.egg-info/SOURCES.txt
dnsmon.egg-info/dependency_links.txt
dnsmon.egg-info/requires.txt
dnsmon.egg-info/top_level.txt