Metadata-Version: 1.0
Name: dnsmon
Version: 0.1
Summary: A package to monitor DNS resolution values and report on differences from expected values
Home-page: http://github.com/jwyllie83/dnsmon
Author: Jim Wyllie
Author-email: jwyllie83@gmail.com
License: UNKNOWN
Platform: UNKNOWN
Classifier: Environment :: No Input/Output (Daemon)
Classifier: Intended Audience :: Developers
Classifier: License :: OSI Approved :: GNU General Public License (GPL)
Classifier: Natural Language :: English
